ibltuning/__init__.py
ibltuning/ibldataset/__init__.py
ibltuning/ibldataset/codemodel/branch.py
ibltuning/ibldataset/codemodel/branch_easy.py
ibltuning/ibldataset/codemodel/branchlinear.py
ibltuning/ibldataset/codemodel/linear.py
ibltuning/ibldataset/ibldataset.py
ibltuning/ibldataset/psuedodata.py
ibltuning/iblmodel/__init__.py
ibltuning/iblmodel/iblboosting.py
ibltuning/utils/__init__.py
ibltuning/utils/code_model.txt
ibltuning/utils/utils.py
ibltuning-0.1.8.dist-info/LICENSE
ibltuning-0.1.8.dist-info/METADATA
ibltuning-0.1.8.dist-info/WHEEL
ibltuning-0.1.8.dist-info/RECORD
