Metadata-Version: 2.1
Name: ibltuning
Version: 0.1.8
Summary: 
Author: toma tanaka
Author-email: ulti4929@gmail.com
Requires-Python: >=3.9,<4.0
Classifier: Programming Language :: Python :: 3
Classifier: Programming Language :: Python :: 3.9
Classifier: Programming Language :: Python :: 3.10
Classifier: Programming Language :: Python :: 3.11
Requires-Dist: datasets (>=2.16.1,<3.0.0)
Requires-Dist: huggingface-hub (>=0.20.2,<0.21.0)
Requires-Dist: jinja2 (>=3.1.3,<4.0.0)
Requires-Dist: numpy (==1.23.5)
Requires-Dist: pandas (>=2.1.4,<3.0.0)
